Workbook
Name WACC: DCF!$B$19

Sheet Inputs
A1: Input | B1: Value | C1: Source
A2: Base-year net sales, excluding businesses being sold (USD m) | B2: 44308.7 | C2: FY25 10-K net operating revenues 47,941 less CCBA 3632.3 (EUR 3,357m x 1.0820 USD/EUR, FRED DEXUSEU 2024 average). Coca-Cola HBC CCBA acquisition announcement, 21 Oct 2025 (factsheet https://www.coca-colahellenic.com/content/dam/cch/us/documents/investors-and-financial/2026-q1-trading-update/coca-cola-hbc-factsheet-ccba-acquisition-q1-2026.pdf.downloadasset.pdf and acquisition presentation): CCBA 2024 net sales revenue EUR 3,357m, EBIT EUR 246m; KO sells 41.5% for USD 1.3bn, keeps 25%; 100% equity value USD 3.4bn. Seen via web search; page not reachable from this environment, PM asked to verify. FLAG: CCBA figure is calendar 2024. PM decision 2026-10-13
A3: Base operating margin before exceptionals | B3: 0.33191 | C3: (comparable operating income 15,013 - CCBA EBIT 266.2) / (comparable revenues 48,062 - CCBA 3632.3); Q4 2025 8-K 0001628280-26-006642 + Coca-Cola HBC CCBA acquisition announcement, 21 Oct 2025 (factsheet https://www.coca-colahellenic.com/content/dam/cch/us/documents/investors-and-financial/2026-q1-trading-update/coca-cola-hbc-factsheet-ccba-acquisition-q1-2026.pdf.downloadasset.pdf and acquisition presentation): CCBA 2024 net sales revenue EUR 3,357m, EBIT EUR 246m; KO sells 41.5% for USD 1.3bn, keeps 25%; 100% equity value USD 3.4bn. Seen via web search; page not reachable from this environment, PM asked to verify. PM rule: held flat. PM decision 2026-10-13
A4: Tax rate | B4: 0.237 | C4: PM decision (IRS case assumed lost): 19.9% underlying effective tax rate, FY26 guidance (KO Q2 2026 results 8-K ex.99.1 (accession 0001628280-26-049922, https://www.sec.gov/Archives/edgar/data/21344/000162828026049922/a2026q2earningsreleaseex-9.htm), outlook table) + 3.8 points if the Tax Court methodology keeps applying (KO Q2 2026 10-Q (accession 0001628280-26-050503, https://www.sec.gov/Archives/edgar/data/21344/000162828026050503/ko-20260703.htm) Note 9 Commitments and Contingencies (brief says note 12): 'would increase the Company's effective tax rate by approximately 3.8%')
A5: D&A % of sales | B5: 0.02682 | C5: FY21-FY25 depreciation & amortisation / net operating revenues, pooled over 5 years (XBRL us-gaap:DepreciationDepletionAndAmortization and us-gaap:Revenues, 10-Ks FY22-FY25; financials_raw.csv)
A6: Capex % of sales | B6: 0.04405 | C6: FY25 purchases of property, plant and equipment 2,112 / net operating revenues 47,941, KO FY25 10-K (accession 0001628280-26-010047; XBRL us-gaap:PaymentsToAcquirePropertyPlantAndEquipment, us-gaap:Revenues). PM decision 2026-10-13 (evidence audit): latest actual instead of the 5-year average (3.99%), which included Covid-era 2021; FY26 guidance capex c.$2.2bn (Q2 2026 8-K 0001628280-26-049922)
A7: Terminal-year capex % of sales | B7: 0.047590042 | C7: PM rule: return on new investment 27.0% (value driver formula, briefs/KO.yaml)
A8: Net working capital % of sales | B8: -0.10256 | C8: FY25 (inventories 4,425 + trade receivables 3,038 + prepaid & other current 2,433 - accounts payable & accrued 14,813 = -4,917) / net operating revenues 47,941; KO FY25 10-K (accession 0001628280-26-010047, filed 2026-02-20, https://www.sec.gov/Archives/edgar/data/21344/000162828026010047/ko-20251231.htm) balance sheet. Negative = suppliers fund KO. FY24 cross-check ex-fairlife liability 6,126: -4,291 = -9.12% of sales.
A9: Savings flow-through | B9: 0 | C9: PM assumption (briefs/KO.yaml)
A10: Risk-free rate (US 10y) | B10: 0.0522 | C10: FRED DGS10 (US 10-year Treasury, constant maturity), 2026-10-08
A11: Equity risk premium | B11: 0.05 | C11: PM assumption (briefs/KO.yaml)
A12: Beta | B12: 0.86841733 | C12: BEAR SCRATCH SCENARIO ONLY, not the base: Damodaran soft-beverage unlevered 0.8204851316412943 x 1.0584
A13: Pre-tax cost of debt | B13: 0.0591 | C13: risk-free 5.22% + credit spread 0.69% (PM rule, briefs)
... A21: Minority interests at book (USD m) | B21: 2106 | C21: KO FY25 10-K (accession 0001628280-26-010047, filed 2026-02-20, https://www.sec.gov/Archives/edgar/data/21344/000162828026010047/ko-20251231.htm) balance sheet: equity attributable to noncontrolling interests 2,106 (book; includes the 40% India bottling NCI sold July 2025 and the outside shareholders of CCBA - see FLAG) FLAG (PM informed 2026-10-13): includes CCBA's outside shareholder (Gutsche 33.5%), not disclosed; full amount deducted (conservative, up to c.USD 1.1bn too much).
A22: Minorities' share of operating profit (proportionate method; blank = use book) | C22: PM assumption (briefs/KO.yaml)
A23: Pension deficit (USD m) | B23: 0 | C23: KO FY25 10-K (accession 0001628280-26-010047, filed 2026-02-20, https://www.sec.gov/Archives/edgar/data/21344/000162828026010047/ko-20251231.htm) Note 14: pension plans net ASSET 295, other postretirement net liability 112 = net surplus 183; brief rule 0 if in surplus. Gross accrued liability of deficit plans 863 (MD&A) - see notes.
A24: Associates and equity stakes (USD m) | B24: 46625.5 | C24: Listed stakes at run-date market value 39539.5 (data/associates_rollforward_check.csv: 31 Dec 2025 fair values from FY25 10-K x price and FX change to 13 Oct 2026, Yahoo/FRED) + unlisted equity-method investments at book 6,236 (FY25 10-K: 20,235 - listed book 13,999) + retained 25% of CCBA at deal value 850 (0.25 x USD 3.4bn, Coca-Cola HBC CCBA acquisition announcement, 21 Oct 2025 (factsheet https://www.coca-colahellenic.com/content/dam/cch/us/documents/investors-and-financial/2026-q1-trading-update/coca-cola-hbc-factsheet-ccba-acquisition-q1-2026.pdf.downloadasset.pdf and acquisition presentation): CCBA 2024 net sales revenue EUR 3,357m, EBIT EUR 246m; KO sells 41.5% for USD 1.3bn, keeps 25%; 100% equity value USD 3.4bn. Seen via web search; page not reachable from this environment, PM asked to verify). PM rule: listed stakes at run-date market value
A25: Disposal proceeds not in net debt (USD m) | B25: 1300 | C25: KO's 41.5% of CCBA sold for USD 1.3bn, not yet received (Q2 2026 10-Q: not closed). Coca-Cola HBC CCBA acquisition announcement, 21 Oct 2025 (factsheet https://www.coca-colahellenic.com/content/dam/cch/us/documents/investors-and-financial/2026-q1-trading-update/coca-cola-hbc-factsheet-ccba-acquisition-q1-2026.pdf.downloadasset.pdf and acquisition presentation): CCBA 2024 net sales revenue EUR 3,357m, EBIT EUR 246m; KO sells 41.5% for USD 1.3bn, keeps 25%; 100% equity value USD 3.4bn. Seen via web search; page not reachable from this environment, PM asked to verify. PM decision 2026-10-13
A26: Restructuring cash still to pay (USD m) | B26: 0 | C26: KO FY25 10-K (accession 0001628280-26-010047, filed 2026-02-20, https://www.sec.gov/Archives/edgar/data/21344/000162828026010047/ko-20251231.htm) Note 19: productivity and reinvestment program (2012-2017) 'substantially completed' at 31 Dec 2025 (FY25 charge 97); no new programme announced in the Q1/Q2 2026 10-Qs.
A27: Contingent liabilities assumed paid, e.g. a lost tax case (USD m) | B27: 14000 | C27: Potential IRS tax and interest 2010-2025 at 31 Dec 2025, KO FY25 10-K (accession 0001628280-26-010047; XBRL ko:IncrementalTaxAndInterestLiability = 14,000m). PM decision 2026-10-13: assume KO loses; H1 2026 accrual (USD 900m, Q2 2026 10-Q) excluded because the 23.7% tax rate already charges 2026 onwards (mistakes log row 17)
A28: Ordinary shares (m) | B28: 4302 | C28: KO FY25 10-K (accession 0001628280-26-010047, filed 2026-02-20, https://www.sec.gov/Archives/edgar/data/21344/000162828026010047/ko-20251231.htm) XBRL: 7,040m issued (us-gaap:CommonStockSharesIssued) - 2,738m treasury (us-gaap:TreasuryStockCommonShares) at 31 Dec 2025. Check: Q2 2026 10-Q cover 4,302,549,243 at 27 Jul 2026.
A29: Share price (USD) | B29: 90.120003 | C29: Yahoo Finance KO close (US dollars), 2026-10-13

Sheet DCF
A1: USD m | B1: FY25 base | C1: FY26 | D1: FY27 | E1: FY28 | F1: FY29 | G1: FY30 | I1: Python check (final year)
A2: Growth | C2: 0.06 | D2: 0.03 | E2: 0.03 | F2: 0.03 | G2: 0.03
A3: Net sales | B3: =Inputs!$B$2 | C3: =B3*(1+C2) | D3: =C3*(1+D2) | E3: =D3*(1+E2) | F3: =E3*(1+F2) | G3: =F3*(1+G2) | I3: 52862.022
A4: Savings kept | C4: =0.0*Inputs!$B$9 | D4: =0.0*Inputs!$B$9 | E4: =0.0*Inputs!$B$9 | F4: =0.0*Inputs!$B$9 | G4: =0.0*Inputs!$B$9
A5: EBIT | C5: =C3*Inputs!$B$3+C4 | D5: =D3*Inputs!$B$3+D4 | E5: =E3*Inputs!$B$3+E4 | F5: =F3*Inputs!$B$3+F4 | G5: =G3*Inputs!$B$3+G4 | I5: 17545.434
A6: Tax | C6: =C5*Inputs!$B$4 | D6: =D5*Inputs!$B$4 | E6: =E5*Inputs!$B$4 | F6: =F5*Inputs!$B$4 | G6: =G5*Inputs!$B$4
A7: NOPAT | C7: =C5-C6 | D7: =D5-D6 | E7: =E5-E6 | F7: =F5-F6 | G7: =G5-G6
A8: D&A | C8: =C3*Inputs!$B$5 | D8: =D3*Inputs!$B$5 | E8: =E3*Inputs!$B$5 | F8: =F3*Inputs!$B$5 | G8: =G3*Inputs!$B$5
A9: Capex | C9: =C3*Inputs!$B$6 | D9: =D3*Inputs!$B$6 | E9: =E3*Inputs!$B$6 | F9: =F3*Inputs!$B$6 | G9: =G3*Inputs!$B$6
A10: Increase in NWC | C10: =(C3-B3)*Inputs!$B$8 | D10: =(D3-C3)*Inputs!$B$8 | E10: =(E3-D3)*Inputs!$B$8 | F10: =(F3-E3)*Inputs!$B$8 | G10: =(G3-F3)*Inputs!$B$8
A11: Unlevered FCF | C11: =C7+C8-C9-C10 | D11: =D7+D8-D9-D10 | E11: =E7+E8-E9-E10 | F11: =F7+F8-F9-F10 | G11: =G7+G8-G9-G10 | I11: 12634.262
A12: Cash flow counted | C12: =C11*(1-Inputs!$B$16) | D12: =D11*1 | E12: =E11*1 | F12: =F11*1 | G12: =G11*1
A13: Discount period | C13: =(0+(1-Inputs!$B$16))/2 | D13: =((1-Inputs!$B$16)+(2-Inputs!$B$16))/2 | E13: =((2-Inputs!$B$16)+(3-Inputs!$B$16))/2 | F13: =((3-Inputs!$B$16)+(4-Inputs!$B$16))/2 | G13: =((4-Inputs!$B$16)+(5-Inputs!$B$16))/2
A14: Discount factor | C14: =1/(1+WACC)^C13 | D14: =1/(1+WACC)^D13 | E14: =1/(1+WACC)^E13 | F14: =1/(1+WACC)^F13 | G14: =1/(1+WACC)^G13
A15: PV of FCF | C15: =C12*C14 | D15: =D12*D14 | E15: =E12*E14 | F15: =F12*F14 | G15: =G12*G14 | I15: 8501.5686
A16: Valuation | C16: Python check
A17: Cost of equity = Rf + beta x ERP | B17: =Inputs!$B$10+Inputs!$B$12*Inputs!$B$11 | C17: 0.095620867
A18: After-tax cost of debt | B18: =Inputs!$B$13*(1-Inputs!$B$4) | C18: 0.0450933
A19: WACC | B19: =(1-Inputs!$B$14)*B17+Inputs!$B$14*B18 | C19: 0.092027346
A20: Sum of PV of FCF | B20: =SUM(C15:G15) | C20: 48071.915
A21: Terminal-year FCF (normalised, grows at g) | B21: =G7*(1+Inputs!$B$15)+G3*(1+Inputs!$B$15)*Inputs!$B$5-G3*(1+Inputs!$B$15)*Inputs!$B$7-G3*Inputs!$B$15*Inputs!$B$8 | C21: 12643.435
A22: Terminal value (Gordon growth) | B22: =B21/(WACC-Inputs!$B$15) | C22: 175536.59
A23: PV of terminal value | B23: =B22/(1+WACC)^(5-Inputs!$B$16-0.5) | C23: 118118.2
A24: Enterprise value | B24: =B20+B23 | C24: 166190.12
A25: Minority interests deducted | B25: =IF(ISBLANK(Inputs!$B$22),Inputs!$B$21,Inputs!$B$22*B24) | C25: 2106
A26: Equity value at balance sheet date | B26: =B24-Inputs!$B$19-Inputs!$B$20-B25-Inputs!$B$23-Inputs!$B$26-Inputs!$B$27+Inputs!$B$24+Inputs!$B$25 | C26: 166601.62
A27: Equity value at valuation date | B27: =B26*(1+B17)^Inputs!$B$17-Inputs!$B$18 | C27: 172119.58
A28: Value per share (USD) | B28: =B27/Inputs!$B$28 | C28: 40.009201
A29: Upside vs share price | B29: =B28/Inputs!$B$29-1 | C29: -0.55604528
