Workbook
Name WACC: DCF!$B$19

Sheet Inputs
A1: Input | B1: Value | C1: Source
A2: Base-year net sales, excluding businesses being sold (GBP m) | B2: 9590 | C2: GBP m, FY25 revenue 9,590 (RELX FY2025 results 6-K ex 99.1 (accession 0000929869-26-000008, 12 Feb 2026, https://www.sec.gov/Archives/edgar/data/929869/000092986926000008/relx-20260201xex99d1.htm) p.26; RELX Annual Report 2025 (20-F ex 15.2, accession 0001104659-26-017277, filed 19 Feb 2026, https://www.sec.gov/Archives/edgar/data/929869/000110465926017277/relx-20251231xex15d2.htm) p.186; XBRL ifrs-full:RevenueFromContractsWithCustomers). The DCF base is FY25 revenue INCLUDING print (399); the margin decision (35.0%) is on H1 2026 adjusted margin EX print, applied to this base (PM decision, brief dcf.base_margin comment).
A3: Base operating margin before exceptionals | B3: 0.35 | C3: PM decision 14 Oct 2026, briefs/RELX.yaml dcf.base_margin: H1 2026 adjusted operating margin without print (1,727 - 78) / (4,871 - 157) = 35.0% (RELX H1 2026 interim results 6-K ex 99.1 (accession 0000929869-26-000054, 23 Jul 2026, https://www.sec.gov/Archives/edgar/data/929869/000092986926000054/relx-20260723xex99d1.htm) p.1-9). Data agent check: FY25 adjusted margin 3,342 / 9,590 = 34.85% incl. print (AR25 p.186).
A4: Tax rate | B4: 0.228 | C4: PM decision 14 Oct 2026, briefs/RELX.yaml dcf.tax_rate: H1 2026 effective tax rate 22.8%, 'best estimate of the annual tax rate expected for the full financial year' (RELX H1 2026 interim results 6-K ex 99.1 (accession 0000929869-26-000054, 23 Jul 2026, https://www.sec.gov/Archives/edgar/data/929869/000092986926000054/relx-20260723xex99d1.htm) p.28, note 7).
A5: D&A % of sales | B5: 0.0507 | C5: PM decision 14 Oct 2026, briefs/RELX.yaml dcf.da_pct_sales: H1 2026 (internally developed 193 + PP&E 12 + pre-publication 42) / revenue 4,871 = 5.07% (RELX H1 2026 interim results 6-K ex 99.1 (accession 0000929869-26-000054, 23 Jul 2026, https://www.sec.gov/Archives/edgar/data/929869/000092986926000054/relx-20260723xex99d1.htm) p.10 and p.25); lease depreciation (18) excluded because leases are not in net debt.
A6: Capex % of sales | B6: 0.071 | C6: PM decision 14 Oct 2026, briefs/RELX.yaml dcf.capex_pct_sales: H1 2026 (capex 292 incl. capitalised development 280 + pre-publication spend 54) / 4,871 = 7.10% (RELX H1 2026 interim results 6-K ex 99.1 (accession 0000929869-26-000054, 23 Jul 2026, https://www.sec.gov/Archives/edgar/data/929869/000092986926000054/relx-20260723xex99d1.htm) p.10, quote re-checked: 'Capital expenditure was GBP 292m ... excludes pre-publication costs of GBP 54m').
A7: Terminal-year capex % of sales | B7: 0.095116325 | C7: PM rule: return on new investment 15.4% (value driver formula, briefs/RELX.yaml)
A8: Net working capital % of sales | B8: -0.15527 | C8: FY25 (inventories and pre-publication costs 311 + trade and other receivables 2468 - trade and other payables 4268) / revenue 9,590 = -1489 / 9,590 = -15.5266%. RELX Annual Report 2025 (20-F ex 15.2, accession 0001104659-26-017277, filed 19 Feb 2026, https://www.sec.gov/Archives/edgar/data/929869/000110465926017277/relx-20251231xex15d2.htm) p.141 balance sheet, notes 18-20 (p.176; payables include deferred income 2390); XBRL relx:InventoriesAndPrepublicationCosts, ifrs-full:TradeAndOtherCurrentReceivables, TradeAndOtherCurrentPayables. FLAG: the results release balance sheet shows current payables 4260 with 9 non-current (RELX FY2025 results 6-K ex 99.1 (accession 0000929869-26-000008, 12 Feb 2026, https://www.sec.gov/Archives/edgar/data/929869/000092986926000008/relx-20260201xex99d1.htm) p.22) against 4268 + 1 in the audited Annual Report: GBP 8m reclassified between current and non-current. The audited 4,268 is used; with 4,260 the ratio would be -15.4432%.
A9: Savings flow-through | B9: 0 | C9: PM assumption (briefs/RELX.yaml)
A10: Risk-free rate (10-year government bond in GBP, the cash-flow currency) | B10: 0.0545 | C10: PM decision 14 Oct 2026, briefs/RELX.yaml dcf.wacc.risk_free comment: UK 10-year gilt at the 13 Oct 2026 close, 5.45% (Investing.com historical data 5.4542%; Trading Economics 5.44%). FLAG: aggregator figures; the Bank of England and DMO sites are blocked, and Trading Economics did not resolve from the Data agent's environment, so the Data agent could not re-check 5.45% itself. Reference only: FRED IRLTLT01GBM156N (OECD monthly average) Aug 2026 = 4.9886% (stale); FRED DGS10 (US 10-year) 13 Oct 2026 = 5.21%.
A11: Equity risk premium | B11: 0.042 | C11: PM assumption (briefs/RELX.yaml)
A12: Beta | B12: 0.9729 | C12: Risk agent, bottom-up: Damodaran GLOBAL Information Services unlevered beta corrected for cash 0.8737 (86 firms, betaGlobal.xls dated 2026-01-05, sheet 'Industry Averages', PM upload) relevered (Hamada) at RELX's market D/E 0.1470 = net debt ex leases GBP 7,104m (31 Dec 2025, 7,201 less 97 leases, FY25 results 6-K 0000929869-26-000008 p.13) / market cap GBP 48,319.4m (1,743.754727m shares x 2,771p / 100) and tax 22.8% (brief). PM decision 14 Oct 2026 (briefs/RELX.yaml dcf.wacc.beta). The PM card's 0.974 used net debt incl. leases 7,201; at the brief's 7,104 the value is 0.9729. Cross-checks in risk/beta_evidence.json and risk/risk.json (not used).
A13: Pre-tax cost of debt | B13: 0.0615 | C13: risk-free 5.45% + credit spread 0.70% (PM rule, briefs)
... A23: Minority interests at book (GBP m) | B23: 24 | C23: Book value of non-controlling interests at 31 Dec 2025 (RELX FY2025 results 6-K ex 99.1 (accession 0000929869-26-000008, 12 Feb 2026, https://www.sec.gov/Archives/edgar/data/929869/000092986926000008/relx-20260201xex99d1.htm) p.22; RELX Annual Report 2025 (20-F ex 15.2, accession 0001104659-26-017277, filed 19 Feb 2026, https://www.sec.gov/Archives/edgar/data/929869/000110465926017277/relx-20251231xex15d2.htm) p.141; XBRL ifrs-full:NoncontrollingInterests 24). Brief minorities_method: book.
A24: Minorities' share of operating profit (proportionate method; blank = use book) | C24: PM assumption (briefs/RELX.yaml)
A25: Pension deficit (GBP m) | B25: 0 | C25: Brief rule (0 when in surplus): net SURPLUS of 43 at 31 Dec 2025 = net pension assets 197 - net pension obligations 154 (RELX Annual Report 2025 (20-F ex 15.2, accession 0001104659-26-017277, filed 19 Feb 2026, https://www.sec.gov/Archives/edgar/data/929869/000110465926017277/relx-20251231xex15d2.htm) p.141; XBRL ifrs-full:LiabilityAssetOfDefinedBenefitPlans = -43; FY25R p.29-30).
A26: Associates and equity stakes (GBP m) | B26: 131 | C26: Venture capital and other investments at book = fair value, 131 at 31 Dec 2025 (RELX Annual Report 2025 (20-F ex 15.2, accession 0001104659-26-017277, filed 19 Feb 2026, https://www.sec.gov/Archives/edgar/data/929869/000110465926017277/relx-20251231xex15d2.htm) p.167, note 15; p.141 'Other investments'). Joint ventures and associates (book 164) are NOT added: their profit is inside adjusted operating profit (JV share of adjusted operating profit 57, RELX Annual Report 2025 (20-F ex 15.2, accession 0001104659-26-017277, filed 19 Feb 2026, https://www.sec.gov/Archives/edgar/data/929869/000110465926017277/relx-20251231xex15d2.htm) p.206; reconciliation reclassifies JV tax +14 and finance income -1 into adjusted OP, RELX FY2025 results 6-K ex 99.1 (accession 0000929869-26-000008, 12 Feb 2026, https://www.sec.gov/Archives/edgar/data/929869/000092986926000008/relx-20260201xex99d1.htm) p.26).
A27: Disposal proceeds not in net debt (GBP m) | B27: 0 | C27: Brief: no pending disposal. No assets held for sale at 31 Dec 2025 (RELX Annual Report 2025 (20-F ex 15.2, accession 0001104659-26-017277, filed 19 Feb 2026, https://www.sec.gov/Archives/edgar/data/929869/000110465926017277/relx-20251231xex15d2.htm) p.141 balance sheet; no XBRL held-for-sale facts for FY25).
A28: Restructuring cash still to pay (GBP m) | B28: 0 | C28: Brief: no announced one-off restructuring programme (none in FY25R or H126).
A29: Contingent liabilities assumed paid, e.g. a lost tax case (GBP m) | B29: 0 | C29: not in this brief's bridge (0)
A30: Ordinary shares (m) | B30: 1743.7547 | C30: RELX 'Transactions in own shares' 28 Sep 2026, 6-K ex 99.6 (accession 0000929869-26-000071, https://www.sec.gov/Archives/edgar/data/929869/000092986926000071/relx-ex99d6.htm): 'RELX PLC holds 85,329,583 ordinary shares in treasury, and has 1,743,754,727 ordinary shares in issue (excluding treasury shares)' after buybacks to 25 Sep 2026. Ordinary shares; 1 ADR = 1 share (not used). Includes shares held by the Employee Benefit Trust (4.89m at 31 Dec 2025, RELX Annual Report 2025 (20-F ex 15.2, accession 0001104659-26-017277, filed 19 Feb 2026, https://www.sec.gov/Archives/edgar/data/929869/000110465926017277/relx-20251231xex15d2.htm) p.179): FLAG in notes.md. Purchases from 28 Sep to 13 Oct 2026 not yet filed.
A31: GBP per GBP | B31: 1 | C31: 1: the company reports in pounds, so no exchange rate is needed to reach pence
A32: Share price (pence) | B32: 2771 | C32: Yahoo Finance REL.L close 2026-10-13 (pence, GBp), the 13 Oct 2026 CLOSE (desk.data_sources last_close, unadjusted). Not an intraday 14 Oct price.

Sheet DCF
A1: GBP m | B1: FY25 base | C1: FY26 | D1: FY27 | E1: FY28 | F1: FY29 | G1: FY30 | I1: Python check (final year)
A2: Growth | C2: 0.03 | D2: 0.05 | E2: 0.05 | F2: 0.05 | G2: 0.05
A3: Net sales | B3: =Inputs!$B$2 | C3: =B3*(1+C2) | D3: =C3*(1+D2) | E3: =D3*(1+E2) | F3: =E3*(1+F2) | G3: =F3*(1+G2) | I3: 12006.406
A4: Savings kept | C4: =0.0*Inputs!$B$9 | D4: =0.0*Inputs!$B$9 | E4: =0.0*Inputs!$B$9 | F4: =0.0*Inputs!$B$9 | G4: =0.0*Inputs!$B$9
A5: EBIT | C5: =C3*Inputs!$B$3+C4 | D5: =D3*Inputs!$B$3+D4 | E5: =E3*Inputs!$B$3+E4 | F5: =F3*Inputs!$B$3+F4 | G5: =G3*Inputs!$B$3+G4 | I5: 4202.2421
A6: Tax | C6: =C5*Inputs!$B$4 | D6: =D5*Inputs!$B$4 | E6: =E5*Inputs!$B$4 | F6: =F5*Inputs!$B$4 | G6: =G5*Inputs!$B$4
A7: NOPAT | C7: =C5-C6 | D7: =D5-D6 | E7: =E5-E6 | F7: =F5-F6 | G7: =G5-G6
A8: D&A | C8: =C3*Inputs!$B$5 | D8: =D3*Inputs!$B$5 | E8: =E3*Inputs!$B$5 | F8: =F3*Inputs!$B$5 | G8: =G3*Inputs!$B$5
A9: Capex | C9: =C3*Inputs!$B$6 | D9: =D3*Inputs!$B$6 | E9: =E3*Inputs!$B$6 | F9: =F3*Inputs!$B$6 | G9: =G3*Inputs!$B$6
A10: Increase in NWC | C10: =(C3-B3)*Inputs!$B$8 | D10: =(D3-C3)*Inputs!$B$8 | E10: =(E3-D3)*Inputs!$B$8 | F10: =(F3-E3)*Inputs!$B$8 | G10: =(G3-F3)*Inputs!$B$8
A11: Unlevered FCF | C11: =C7+C8-C9-C10 | D11: =D7+D8-D9-D10 | E11: =E7+E8-E9-E10 | F11: =F7+F8-F9-F10 | G11: =G7+G8-G9-G10 | I11: 3089.174
A12: Cash flow counted | C12: =C11*(1-Inputs!$B$16) | D12: =D11*1 | E12: =E11*1 | F12: =F11*1 | G12: =G11*1
A13: Discount period | C13: =(0+(1-Inputs!$B$16))/2 | D13: =((1-Inputs!$B$16)+(2-Inputs!$B$16))/2 | E13: =((2-Inputs!$B$16)+(3-Inputs!$B$16))/2 | F13: =((3-Inputs!$B$16)+(4-Inputs!$B$16))/2 | G13: =((4-Inputs!$B$16)+(5-Inputs!$B$16))/2
A14: Discount factor | C14: =1/(1+WACC)^C13 | D14: =1/(1+WACC)^D13 | E14: =1/(1+WACC)^E13 | F14: =1/(1+WACC)^F13 | G14: =1/(1+WACC)^G13
A15: PV of FCF | C15: =C12*C14 | D15: =D12*D14 | E15: =E12*E14 | F15: =F12*F14 | G15: =G12*G14 | I15: 2102.8818
A16: Valuation | C16: Python check
A17: Cost of equity = Rf + beta x ERP | B17: =Inputs!$B$10+Inputs!$B$12*Inputs!$B$11 | C17: 0.0953618
A18: After-tax cost of debt | B18: =Inputs!$B$13*(1-Inputs!$B$4) | C18: 0.047478
A19: WACC | B19: =(1-Inputs!$B$14)*B17+Inputs!$B$14*B18 | C19: 0.089224055
A20: Sum of PV of FCF | B20: =SUM(C15:G15) | C20: 11302.688
A21: Terminal-year FCF (normalised, grows at g) | B21: =G7*(1+Inputs!$B$15)+G3*(1+Inputs!$B$15)*Inputs!$B$5-G3*(1+Inputs!$B$15)*Inputs!$B$7-G3*Inputs!$B$15*Inputs!$B$8 | C21: 2817.45
A22: Terminal value (Gordon growth) | B22: =B21/(WACC-Inputs!$B$15) | C22: 42737.814
A23: PV of terminal value | B23: =B22/(1+WACC)^(5-Inputs!$B$16-0.5) | C23: 29092.751
A24: Enterprise value | B24: =B20+B23 | C24: 40395.44
A25: Minority interests deducted | B25: =IF(ISBLANK(Inputs!$B$24),Inputs!$B$23,Inputs!$B$24*B24) | C25: 24
A26: Equity value at balance sheet date | B26: =B24-Inputs!$B$21-Inputs!$B$22-B25-Inputs!$B$25-Inputs!$B$28-Inputs!$B$29+Inputs!$B$26+Inputs!$B$27 | C26: 33398.44
A27: Equity value at valuation date | B27: =(B26-Inputs!$B$20)*(1+B17)^Inputs!$B$17+Inputs!$B$20-Inputs!$B$18-Inputs!$B$19 | C27: 32596.019
A28: Value per share (GBP) | B28: =B27/Inputs!$B$30 | C28: 18.693007
A29: Value per share (pence) | B29: =B28/Inputs!$B$31*100 | C29: 1869.3007
A30: Upside vs share price | B30: =B29/Inputs!$B$32-1 | C30: -0.32540574
