Workbook

Sheet 1 How to check
B1: Diageo DCF: checking the desk against your own Excel model
B2: Pass test (brief section 6): your value per share must be within 2% of the desk's 1,627.3p, i.e. between 1,594.7p and 1,659.8p. Any gap gets explained. (Updated 13 Oct 2026 for your mid-year decision; it was 1,544.8p with year-end discounting.)
B4: IF YOU ALREADY HAVE A MODEL: type the inputs from tab 2 into it, then fill in the yellow column on tab 3. Steps 1-9 below tell you the conventions the desk used, so differences are about maths, not set-up.
B5: IF YOU DON'T: build it fresh in a new sheet from tab 2 only. Don't open dcf.xlsx until you have your answer, or the check is no longer independent.
A6: 1 | B6: Sales: FY26 base USD 18,505.5m (excludes EABL, which is being sold). Grow by 0%, 1.5%, 2.5%, 3%, 3% for FY27 to FY31.
A7: 2 | B7: Operating profit (EBIT) = sales x 29.36% base margin + savings kept. Savings kept = cumulative savings (377.5, 962.5, 1,000, 1,000, 1,000) x 46% flow-through. The margin is NOT grown; only the savings lift it.
A8: 3 | B8: NOPAT = EBIT x (1 - 24.3% tax).
A9: 4 | B9: Unlevered free cash flow = NOPAT + D&A (3.377% of sales) - capex (7.106% of sales) - increase in working capital. Increase in working capital = (this year's sales - last year's sales) x 37.576%. FY27 uses FY26 sales of 18,505.5 as "last year", so it is 0.
A10: 5 | B10: WACC: cost of equity = 5.22% + 0.9601 x 5.0% = 10.02%. After-tax cost of debt = (5.22% + 1.0%) x (1 - 24.3%) = 4.71%. WACC = 70.6% x Ke + 29.4% x Kd after tax = 8.46%. Keep full decimals (debt weight 0.29395).
A11: 6 | B11: Discounting: valued at 30 June 2026, MID-YEAR convention (your decision, 13 Oct 2026). FY27 cash flow discounted 0.5 years, FY28 1.5 years ... FY31 4.5 years. No stub period.
A12: 7 | B12: Terminal value at end of FY31 (Gordon growth, g = 2%): FY32 cash flow / (WACC - 2%), then discounted 4.5 years (it moves half a year too, like the forecast years). FY32 is a steady-state year: NOPAT and D&A = FY31 x 1.02; capex = FY32 sales x 6.2117% (so new investment earns 13.4%); working-capital increase = FY31 sales x 2% x 37.576%. Expected FY32 cash flow: USD 4,241m.
A13: 8 | B13: Enterprise value to equity (USD m): EV - net debt 20,482 - minorities (2.566% x EV) - restructuring cash 850 + associates 5,284 + disposal proceeds 3,318.3 = equity at 30 June.
A14: 9 | B14: Roll forward to 12 Oct 2026: equity x (1 + cost of equity)^0.2822. Divide by 2,222m shares = USD per share. Divide by 1.3234 (USD per GBP) and x 100 = pence.
B16: If you are more than 2% out, compare line by line on tab 3: the first line that goes red is where the difference starts. Tell me that line and I'll explain the gap.
B17: Common causes: leaving the terminal value at 5 years (gives about 1,566p), discounting FY27 by 0.72 years (old stub method), growing the margin, applying working capital to the level of sales instead of the change, using book minorities (2,083), or rounding WACC to 8.5% (worth about 12p).

Sheet 2 Inputs
A1: Input | B1: Value | C1: Units | D1: Source
A2: Base-year net sales ex-EABL (USD m) | B2: 18505.5 | C2: USD m | D2: Diageo Form 20-F FY26 (SEC accession 0001628280-26-057529, filed 2026-08-18) net sales 19,643 less EABL FY26 net revenue KES 145.96bn / 128.32 KES per USD = 1137.5 (EABL: non-filing source, press reports of EABL FY26 results 6 Aug 2026; FX: Yahoo KES=X FY26 average)
A3: Base operating margin before exceptionals | B3: 0.29358 | C3: % | D3: (Diageo Form 20-F FY26 (SEC accession 0001628280-26-057529, filed 2026-08-18) operating profit before exceptionals 5,683 less EABL EBIT KES 32.1bn / 128.32 = 250.2) / ex-EABL net sales
A4: Tax rate | B4: 0.243 | C4: % | D4: Diageo Form 20-F FY26 (SEC accession 0001628280-26-057529, filed 2026-08-18) p.22, tax rate before exceptional items FY26
A5: D&A % of sales | B5: 0.03377 | C5: % | D5: FY22-FY26 depreciation & amortisation (excl. impairment) / net sales, summed over 5 years; 20-F XBRL deo:DepreciationAndIntangibleAssetAmortisationExpense and deo:NetSales
A6: Capex % of sales | B6: 0.07106 | C6: % | D6: FY22-FY26 purchase of PP&E and software / net sales, summed over 5 years; 20-F cash flow statements
A7: Terminal-year capex % of sales | B7: 0.062116881 | C7: % | D7: PM rule: return on new investment 13.4% (value driver formula, briefs/DGE.yaml)
A8: Net working capital % of sales | B8: 0.37576 | C8: % | D8: FY26 (inventories incl. maturing 10,529 + trade & other receivables 3,277 - trade & other payables 6,425) / net sales 19,643; Diageo Form 20-F FY26 (SEC accession 0001628280-26-057529, filed 2026-08-18) balance sheet
A9: Savings flow-through | B9: 0.46 | C9: % | D9: PM assumption (briefs/DGE.yaml)
A10: Risk-free rate (US 10y) | B10: 0.0522 | C10: % | D10: FRED DGS10 (US 10-year Treasury, constant maturity), 2026-10-08
A11: Equity risk premium | B11: 0.05 | C11: % | D11: PM assumption (briefs/DGE.yaml)
A12: Beta | B12: 0.9601 | C12: x | D12: Risk agent, bottom-up: Damodaran global alcoholic beverages unlevered beta 0.73 (Jan 2026, cash-corrected) relevered at Diageo D/E 0.416, tax 24.3%. See risk/beta_evidence.json
A13: Pre-tax cost of debt | B13: 0.0622 | C13: % | D13: risk-free 5.22% + credit spread 1.00% (PM rule, briefs)
... A15: Terminal growth | B15: 0.02 | C15: % | D15: PM assumption (briefs/DGE.yaml)
A16: Years from 30 June to valuation date (equity roll-forward) | B16: 0.2822 | D16: 103 days of FY27 (from 1 Jul 2026) elapsed at run date 2026-10-12 / 365
A17: Net debt (USD m) | B17: 20482 | C17: USD m | D17: Diageo Form 20-F FY26 (SEC accession 0001628280-26-057529, filed 2026-08-18) note 17 p.187: net borrowings 20,482 (INCLUDES lease liabilities 685; EABL/RCB loans of 272 sit in liabilities held for sale)
A18: Minorities' share of operating profit (proportionate method; blank = use book) | B18: 0.02566 | C18: % | D18: Proportionate minorities (brief: minorities_method). (Profit before exceptional operating items attributable to non-controlling interests 227, Diageo Form 20-F FY26 (SEC accession 0001628280-26-057529) p.210 ROIC table, less EABL's 35% outside shareholders x EABL EBIT 250.2 (Diageo Kenya owns 65% of EABL, 20-F p.164; EBIT as in base_margin) = 139.4) / (operating profit before exceptionals 5,683 - EABL 250.2 = 5,432.8). Simplification: assumes EABL's minorities share EABL's EBIT pro rata.
A19: Associates incl. Moet Hennessy (USD m) | B19: 5284 | C19: USD m | D19: Diageo Form 20-F FY26 (SEC accession 0001628280-26-057529, filed 2026-08-18) note 'Investments in associates': Moet Hennessy 34% at 5,107 (carrying value tested at fair value less costs of disposal, 'sensitive' = little headroom) + others 177
A20: Disposal proceeds not in net debt (USD m) | B20: 3318.3 | C20: USD m | D20: EABL + Kenyan spirits sale to Asahi c.$2.3bn (20-F p.85) + Diageo's 57.21% of USL's RCB sale INR 166.6bn = c.$1.78bn (USL/press, 24 Mar 2026); both gross, before tax and costs, not in net debt at 30 June 2026
A21: Restructuring cash still to pay (USD m) | B21: 850 | C21: USD m | D21: Diageo Capital Markets Day 6-K, 6 Aug 2026 (SEC accession 0001654954-26-007324): c.$800m exceptional cash costs for the operating framework + c.$50m for supply chain in FY27; FY27-29 cumulative free cash flow c.$8bn after c.$850m exceptional cash costs (also 20-F FY26 CEO letter). Pre-tax, undiscounted: any tax relief (up to c.$207m at 24.3%) is not confirmed, so not counted. Not in net debt at 30 June 2026; the forecast is before exceptionals.
A22: Ordinary shares (m) | B22: 2222 | C22: m shares | D22: Diageo Form 20-F FY26 (SEC accession 0001628280-26-057529, filed 2026-08-18) p.188 and XBRL: 2,432m issued - 208m treasury - 2m employee trusts (ordinary shares, NOT ADRs)
A23: USD per GBP | B23: 1.3234 | C23: USD per GBP | D23: FRED DEXUSUK (USD per GBP, noon buying rate New York), 2026-10-02
A24: Share price (pence) | B24: 1673 | C24: pence (GBp) | D24: Yahoo Finance DGE.L close (pence, GBp), 2026-10-12
A25: Organic growth FY27/FY28/FY29/FY30/FY31 | B25: 0% / 1.5% / 2.5% / 3% / 3% | C25: % | D25: briefs/DGE.yaml: low end of management guidance (PM decision 12 Oct 2026)
A26: Cumulative savings FY27/FY28/FY29/FY30/FY31 | B26: 377.5 / 962.5 / 1,000 / 1,000 / 1,000 | C26: USD m | D26: Capital Markets Day 6-K, 6 Aug 2026 (briefs/DGE.yaml)
A27: Terminal return on new investment (RONIC) | B27: 0.134 | C27: % | D27: PM decision 12 Oct 2026: Diageo FY26 ROIC, 20-F FY26 KPI table. Sets terminal capex (row above)
A29: Zero items (no adjustment needed): pension (net surplus), leases (already in net debt), dividends between 30 June and 12 Oct (final dividend goes ex on 15 Oct).

Sheet 3 Compare
A1: Line (USD m unless stated) | B1: Desk value | C1: CLAUDE'S value (tab 4) | D1: Gap % | E1: Check
A2: Net sales FY27 | B2: 18505.5 | C2: ='4 Claude model'!C6 -> 18505.5 | D2: =IF(C2="","",C2/B2-1) -> 0 | E2: =IF(C2="","",IF(ABS(D2)<=0.005,"OK","Gap: look here first" )) -> OK
A3: Net sales FY28 | B3: 18783.083 | C3: ='4 Claude model'!D6 -> 18783.083 | D3: =IF(C3="","",C3/B3-1) -> 0 | E3: =IF(C3="","",IF(ABS(D3)<=0.005,"OK","Gap: look here first" )) -> OK
A4: Net sales FY29 | B4: 19252.66 | C4: ='4 Claude model'!E6 -> 19252.66 | D4: =IF(C4="","",C4/B4-1) -> 0 | E4: =IF(C4="","",IF(ABS(D4)<=0.005,"OK","Gap: look here first" )) -> OK
A5: Net sales FY30 | B5: 19830.239 | C5: ='4 Claude model'!F6 -> 19830.239 | D5: =IF(C5="","",C5/B5-1) -> 0 | E5: =IF(C5="","",IF(ABS(D5)<=0.005,"OK","Gap: look here first" )) -> OK
A6: Net sales FY31 | B6: 20425.147 | C6: ='4 Claude model'!G6 -> 20425.147 | D6: =IF(C6="","",C6/B6-1) -> 0 | E6: =IF(C6="","",IF(ABS(D6)<=0.005,"OK","Gap: look here first" )) -> OK
A7: EBIT FY27 | B7: 5606.4947 | C7: ='4 Claude model'!C9 -> 5606.4947 | D7: =IF(C7="","",C7/B7-1) -> 0 | E7: =IF(C7="","",IF(ABS(D7)<=0.005,"OK","Gap: look here first" )) -> OK
A8: EBIT FY28 | B8: 5957.0874 | C8: ='4 Claude model'!D9 -> 5957.0874 | D8: =IF(C8="","",C8/B8-1) -> 0 | E8: =IF(C8="","",IF(ABS(D8)<=0.005,"OK","Gap: look here first" )) -> OK
A9: EBIT FY29 | B9: 6112.1958 | C9: ='4 Claude model'!E9 -> 6112.1958 | D9: =IF(C9="","",C9/B9-1) -> 0 | E9: =IF(C9="","",IF(ABS(D9)<=0.005,"OK","Gap: look here first" )) -> OK
A10: EBIT FY30 | B10: 6281.7617 | C10: ='4 Claude model'!F9 -> 6281.7617 | D10: =IF(C10="","",C10/B10-1) -> 0 | E10: =IF(C10="","",IF(ABS(D10)<=0.005,"OK","Gap: look here first" )) -> OK
A11: EBIT FY31 | B11: 6456.4145 | C11: ='4 Claude model'!G9 -> 6456.4145 | D11: =IF(C11="","",C11/B11-1) -> 0 | E11: =IF(C11="","",IF(ABS(D11)<=0.005,"OK","Gap: look here first" )) -> OK
A12: Unlevered FCF FY27 | B12: 3554.0464 | C12: ='4 Claude model'!C15 -> 3554.0464 | D12: =IF(C12="","",C12/B12-1) -> 0 | E12: =IF(C12="","",IF(ABS(D12)<=0.005,"OK","Gap: look here first" )) -> OK
A13: Unlevered FCF FY28 | B13: 3704.7896 | C13: ='4 Claude model'!D15 -> 3704.7896 | D13: =IF(C13="","",C13/B13-1) -> 0 | E13: =IF(C13="","",IF(ABS(D13)<=0.005,"OK","Gap: look here first" )) -> OK
A14: Unlevered FCF FY29 | B14: 3732.5523 | C14: ='4 Claude model'!E15 -> 3732.5523 | D14: =IF(C14="","",C14/B14-1) -> 0 | E14: =IF(C14="","",IF(ABS(D14)<=0.005,"OK","Gap: look here first" )) -> OK
A15: Unlevered FCF FY30 | B15: 3798.7926 | C15: ='4 Claude model'!F15 -> 3798.7926 | D15: =IF(C15="","",C15/B15-1) -> 0 | E15: =IF(C15="","",IF(ABS(D15)<=0.005,"OK","Gap: look here first" )) -> OK
A16: Unlevered FCF FY31 | B16: 3902.3098 | C16: ='4 Claude model'!G15 -> 3902.3098 | D16: =IF(C16="","",C16/B16-1) -> 0 | E16: =IF(C16="","",IF(ABS(D16)<=0.005,"OK","Gap: look here first" )) -> OK
A17: Cost of equity | B17: 0.100205 | C17: ='4 Claude model'!B23 -> 0.100205 | D17: =IF(C17="","",C17/B17-1) -> 0 | E17: =IF(C17="","",IF(ABS(D17)<=0.005,"OK","Gap: look here first" )) -> OK
A18: WACC | B18: 0.084590494 | C18: ='4 Claude model'!B25 -> 0.084590494 | D18: =IF(C18="","",C18/B18-1) -> 0 | E18: =IF(C18="","",IF(ABS(D18)<=0.005,"OK","Gap: look here first" )) -> OK
A19: Sum of PV of FCF FY27-31 | B19: 15306.216 | C19: ='4 Claude model'!B27 -> 15306.216 | D19: =IF(C19="","",C19/B19-1) -> 0 | E19: =IF(C19="","",IF(ABS(D19)<=0.005,"OK","Gap: look here first" )) -> OK
A20: Terminal-year (FY32) FCF | B20: 4241.1879 | C20: ='4 Claude model'!H15 -> 4241.1879 | D20: =IF(C20="","",C20/B20-1) -> 0 | E20: =IF(C20="","",IF(ABS(D20)<=0.005,"OK","Gap: look here first" )) -> OK
A21: Terminal value at end FY31 (undiscounted) | B21: 65662.726 | C21: ='4 Claude model'!B28 -> 65662.726 | D21: =IF(C21="","",C21/B21-1) -> 0 | E21: =IF(C21="","",IF(ABS(D21)<=0.005,"OK","Gap: look here first" )) -> OK
A22: PV of terminal value | B22: 45564.104 | C22: ='4 Claude model'!B29 -> 45564.104 | D22: =IF(C22="","",C22/B22-1) -> 0 | E22: =IF(C22="","",IF(ABS(D22)<=0.005,"OK","Gap: look here first" )) -> OK
A23: Enterprise value at 30 June 2026 | B23: 60870.32 | C23: ='4 Claude model'!B30 -> 60870.32 | D23: =IF(C23="","",C23/B23-1) -> 0 | E23: =IF(C23="","",IF(ABS(D23)<=0.005,"OK","Gap: look here first" )) -> OK
A24: Minorities deducted (2.566% x EV) | B24: 1561.9324 | C24: ='4 Claude model'!B31 -> 1561.9324 | D24: =IF(C24="","",C24/B24-1) -> 0 | E24: =IF(C24="","",IF(ABS(D24)<=0.005,"OK","Gap: look here first" )) -> OK
A25: Equity value at 30 June 2026 | B25: 46578.688 | C25: ='4 Claude model'!B32 -> 46578.688 | D25: =IF(C25="","",C25/B25-1) -> 0 | E25: =IF(C25="","",IF(ABS(D25)<=0.005,"OK","Gap: look here first" )) -> OK
A26: Equity value at 12 Oct 2026 | B26: 47851.01 | C26: ='4 Claude model'!B33 -> 47851.01 | D26: =IF(C26="","",C26/B26-1) -> 0 | E26: =IF(C26="","",IF(ABS(D26)<=0.005,"OK","Gap: look here first" )) -> OK
A27: Value per share (USD) | B27: 21.535108 | C27: ='4 Claude model'!B34 -> 21.535108 | D27: =IF(C27="","",C27/B27-1) -> 0 | E27: =IF(C27="","",IF(ABS(D27)<=0.005,"OK","Gap: look here first" )) -> OK
A28: VALUE PER SHARE (pence) - the pass test | B28: 1627.2561 | C28: ='4 Claude model'!B35 -> 1627.2561 | D28: =IF(C28="","",C28/B28-1) -> 0 | E28: =IF(C28="","",IF(ABS(D28)<=0.02,"OK","Gap: look here first" )) -> OK
A30: Tolerances: 0.5% on each line (to find where a gap starts); 2% on value per share (the brief's pass test).
A31: Desk values: runs/DGE/2026-10-12/valuation/valuation.json (Phase 3 final, merged 13 Oct 2026).

Sheet 4 Claude model
A1: Independent DCF built by Claude from tab 2 only (13 Oct 2026). Every number below is an Excel formula; change an input on tab 2 and it all recalculates. Not linked to the desk's code or dcf.xlsx.
A2: Finance concepts are named in column A. Yellow cells are typed from tab 2 rows 25-26 (written there as text).
B4: FY26 base | C4: FY27 | D4: FY28 | E4: FY29 | F4: FY30 | G4: FY31 | H4: FY32 (terminal)
A5: Organic growth | C5: 0 | D5: 0.015 | E5: 0.025 | F5: 0.03 | G5: 0.03 | H5: ='2 Inputs'!$B$15 -> 0.02
A6: Net sales (USD m) | B6: ='2 Inputs'!$B$2 -> 18505.5 | C6: =B6*(1+C5) -> 18505.5 | D6: =C6*(1+D5) -> 18783.083 | E6: =D6*(1+E5) -> 19252.66 | F6: =E6*(1+F5) -> 19830.239 | G6: =F6*(1+G5) -> 20425.147 | H6: =G6*(1+H5) -> 20833.649
A7: Cumulative savings run-rate (USD m) | C7: 377.5 | D7: 962.5 | E7: 1000 | F7: 1000 | G7: 1000
A8: Savings kept in profit = savings x flow-through | C8: =C7*'2 Inputs'!$B$9 -> 173.65 | D8: =D7*'2 Inputs'!$B$9 -> 442.75 | E8: =E7*'2 Inputs'!$B$9 -> 460 | F8: =F7*'2 Inputs'!$B$9 -> 460 | G8: =G7*'2 Inputs'!$B$9 -> 460
A9: EBIT = sales x base margin + savings kept | C9: =C6*'2 Inputs'!$B$3+C8 -> 5606.4947 | D9: =D6*'2 Inputs'!$B$3+D8 -> 5957.0874 | E9: =E6*'2 Inputs'!$B$3+E8 -> 6112.1958 | F9: =F6*'2 Inputs'!$B$3+F8 -> 6281.7617 | G9: =G6*'2 Inputs'!$B$3+G8 -> 6456.4145
A10: Tax on EBIT | C10: =C9*'2 Inputs'!$B$4 -> 1362.3782 | D10: =D9*'2 Inputs'!$B$4 -> 1447.5722 | E10: =E9*'2 Inputs'!$B$4 -> 1485.2636 | F10: =F9*'2 Inputs'!$B$4 -> 1526.4681 | G10: =G9*'2 Inputs'!$B$4 -> 1568.9087
A11: NOPAT = EBIT x (1 - tax) | C11: =C9-C10 -> 4244.1165 | D11: =D9-D10 -> 4509.5151 | E11: =E9-E10 -> 4626.9322 | F11: =F9-F10 -> 4755.2936 | G11: =G9-G10 -> 4887.5058 | H11: =G11*(1+H5) -> 4985.2559
A12: D&A | C12: =C6*'2 Inputs'!$B$5 -> 624.93074 | D12: =D6*'2 Inputs'!$B$5 -> 634.3047 | E12: =E6*'2 Inputs'!$B$5 -> 650.16231 | F12: =F6*'2 Inputs'!$B$5 -> 669.66718 | G12: =G6*'2 Inputs'!$B$5 -> 689.7572 | H12: =H6*'2 Inputs'!$B$5 -> 703.55234
A13: Capex | C13: =C6*'2 Inputs'!$B$6 -> 1315.0008 | D13: =D6*'2 Inputs'!$B$6 -> 1334.7258 | E13: =E6*'2 Inputs'!$B$6 -> 1368.094 | F13: =F6*'2 Inputs'!$B$6 -> 1409.1368 | G13: =G6*'2 Inputs'!$B$6 -> 1451.4109 | H13: =H20 -> 1294.1213
A14: Increase in net working capital = change in sales x NWC % | C14: =(C6-B6)*'2 Inputs'!$B$8 -> 0 | D14: =(D6-C6)*'2 Inputs'!$B$8 -> 104.3044 | E14: =(E6-D6)*'2 Inputs'!$B$8 -> 176.44828 | F14: =(F6-E6)*'2 Inputs'!$B$8 -> 217.03138 | G14: =(G6-F6)*'2 Inputs'!$B$8 -> 223.54232 | H14: =(H6-G6)*'2 Inputs'!$B$8 -> 153.49906
A15: Unlevered free cash flow = NOPAT + D&A - capex - increase in NWC | C15: =C11+C12-C13-C14 -> 3554.0464 | D15: =D11+D12-D13-D14 -> 3704.7896 | E15: =E11+E12-E13-E14 -> 3732.5523 | F15: =F11+F12-F13-F14 -> 3798.7926 | G15: =G11+G12-G13-G14 -> 3902.3098 | H15: =H11+H12-H13-H14 -> 4241.1879
A16: Discount period, years from 30 June 2026 (mid-year convention) | C16: 0.5 | D16: 1.5 | E16: 2.5 | F16: 3.5 | G16: 4.5
A17: Discount factor = 1 / (1 + WACC)^period | C17: =1/(1+$B$25)^C16 -> 0.96021194 | D17: =1/(1+$B$25)^D16 -> 0.88532211 | E17: =1/(1+$B$25)^E16 -> 0.81627316 | F17: =1/(1+$B$25)^F16 -> 0.75260955 | G17: =1/(1+$B$25)^G16 -> 0.69391125
A18: PV of free cash flow | C18: =C15*C17 -> 3412.6378 | D18: =D15*D17 -> 3279.9321 | E18: =E15*E17 -> 3046.7822 | F18: =F15*F17 -> 2859.0076 | G18: =G15*G17 -> 2707.8566
A19: Terminal reinvestment = g / RONIC x NOPAT (value driver formula) | H19: =H5/'2 Inputs'!$B$27*H11 -> 744.06805
A20: Terminal capex = D&A + reinvestment - increase in NWC (derived here, not taken from the desk) | H20: =H12+H19-H14 -> 1294.1213
A21: Terminal capex as % of sales (desk input on tab 2 shown for comparison) | G21: ='2 Inputs'!$B$7 -> 0.062116881 | H21: =H20/H6 -> 0.062116881
A23: Cost of equity = risk-free + beta x ERP (CAPM) | B23: ='2 Inputs'!$B$10+'2 Inputs'!$B$12*'2 Inputs'!$B$11 -> 0.100205
A24: After-tax cost of debt = pre-tax x (1 - tax) | B24: ='2 Inputs'!$B$13*(1-'2 Inputs'!$B$4) -> 0.0470854
A25: WACC = equity weight x Ke + debt weight x Kd after tax | B25: =(1-'2 Inputs'!$B$14)*B23+'2 Inputs'!$B$14*B24 -> 0.084590494
A26: Check: debt weight from market values = net debt / (net debt + shares x price x FX) | B26: ='2 Inputs'!$B$17/('2 Inputs'!$B$17+'2 Inputs'!$B$22*'2 Inputs'!$B$24/100*'2 Inputs'!$B$23) -> 0.29395154
A27: Sum of PV of free cash flow FY27-31 | B27: =SUM(C18:G18) -> 15306.216
A28: Terminal value at end FY31 = FY32 FCF / (WACC - g) (Gordon growth) | B28: =H15/(B25-H5) -> 65662.726
A29: PV of terminal value, discounted 4.5 years (mid-year: the perpetuity also arrives mid-year) | B29: =B28/(1+B25)^4.5 -> 45564.104
A30: Enterprise value at 30 June 2026 | B30: =B27+B29 -> 60870.32
A31: Minorities (proportionate) = share of operating profit x EV | B31: ='2 Inputs'!$B$18*B30 -> 1561.9324
A32: Equity value at 30 June = EV - net debt - minorities - restructuring cash + associates + disposal proceeds | B32: =B30-'2 Inputs'!$B$17-B31-'2 Inputs'!$B$21+'2 Inputs'!$B$19+'2 Inputs'!$B$20 -> 46578.688
A33: Equity value at 12 Oct 2026 = rolled forward at the cost of equity | B33: =B32*(1+B23)^'2 Inputs'!$B$16 -> 47851.01
A34: Value per share (USD) | B34: =B33/'2 Inputs'!$B$22 -> 21.535108
A35: VALUE PER SHARE (pence) = USD / (USD per GBP) x 100 | B35: =B34/'2 Inputs'!$B$23*100 -> 1627.2561
A36: Upside vs share price | B36: =B35/'2 Inputs'!$B$24-1 -> -0.027342411
A37: Rating rule: BUY if >= +15%, SELL if <= -10%, else HOLD | B37: =IF(B36>=0.15,"BUY",IF(B36<=-0.1,"SELL","HOLD")) -> HOLD
A38: Cross-check: same model with END-OF-YEAR discounting (Phase 3 basis, should be about 1,544.8p) | B38: =((((C15/(1+B25)^1+D15/(1+B25)^2+E15/(1+B25)^3+F15/(1+B25)^4+G15/(1+B25)^5+B28/(1+B25)^5))*(1-'2 Inputs'!$B$18)-'2 Inputs'!$B$17-'2 Inputs'!$B$21+'2 Inputs'!$B$19+'2 Inputs'!$B$20)*(1+B23)^'2 Inputs'!$B$16/'2 Inputs'!$B$22/'2 Inputs'!$B$23*100) -> 1544.8162
A39: Terminal value share of EV | B39: =B29/B30 -> 0.74854385
A40: Implied exit multiple = terminal value / FY31 EBITDA | B40: =B28/(G9+G12) -> 9.1885178
